setup.py
opencv_engine/__init__.py
opencv_engine/engine.py
opencv_engine.egg-info/PKG-INFO
opencv_engine.egg-info/SOURCES.txt
opencv_engine.egg-info/dependency_links.txt
opencv_engine.egg-info/requires.txt
opencv_engine.egg-info/top_level.txt
tests/__init__.py
tests/integration/__init__.py
tests/integration/opencv_test.py
tests/unit/__init__.py