Metadata-Version: 1.1
Name: opencv-engine
Version: 1.0.1
Summary: OpenCV imaging engine for thumbor.
Home-page: UNKNOWN
Author: Globo.com
Author-email: timehome@corp.globo.com
License: MIT
Keywords: thumbor imaging opencv
Platform: UNKNOWN
Classifier: Development Status :: 4 - Beta
Classifier: Intended Audience :: Developers
Classifier: License :: OSI Approved :: MIT License
Classifier: Natural Language :: English
Classifier: Operating System :: MacOS
Classifier: Operating System :: POSIX
Classifier: Operating System :: Unix
Classifier: Operating System :: OS Independent
Classifier: Programming Language :: Python :: 2.7
